oslo_i18n/__init__.py
oslo_i18n/_factory.py
oslo_i18n/_gettextutils.py
oslo_i18n/_i18n.py
oslo_i18n/_lazy.py
oslo_i18n/_locale.py
oslo_i18n/_message.py
oslo_i18n/_translate.py
oslo_i18n/fixture.py
oslo_i18n/log.py
oslo_i18n/locale/de/LC_MESSAGES/oslo_i18n.po
oslo_i18n/locale/en_GB/LC_MESSAGES/oslo_i18n.po
oslo_i18n/locale/es/LC_MESSAGES/oslo_i18n.po
oslo_i18n/locale/fr/LC_MESSAGES/oslo_i18n.po
oslo_i18n/locale/it/LC_MESSAGES/oslo_i18n.po
oslo_i18n/locale/ja/LC_MESSAGES/oslo_i18n.po
oslo_i18n/locale/ka_GE/LC_MESSAGES/oslo_i18n.po
oslo_i18n/locale/ko_KR/LC_MESSAGES/oslo_i18n.po
oslo_i18n/locale/pl_PL/LC_MESSAGES/oslo_i18n.po
oslo_i18n/locale/pt/LC_MESSAGES/oslo_i18n.po
oslo_i18n/locale/zh_CN/LC_MESSAGES/oslo_i18n.po
oslo_i18n/tests/__init__.py
oslo_i18n/tests/fakes.py
oslo_i18n/tests/test_factory.py
oslo_i18n/tests/test_fixture.py
oslo_i18n/tests/test_gettextutils.py
oslo_i18n/tests/test_handler.py
oslo_i18n/tests/test_lazy.py
oslo_i18n/tests/test_locale_dir_variable.py
oslo_i18n/tests/test_logging.py
oslo_i18n/tests/test_message.py
oslo_i18n/tests/test_public_api.py
oslo_i18n/tests/test_translate.py
oslo_i18n/tests/utils.py
oslo_i18n-6.7.0.dist-info/AUTHORS
oslo_i18n-6.7.0.dist-info/LICENSE
oslo_i18n-6.7.0.dist-info/METADATA
oslo_i18n-6.7.0.dist-info/WHEEL
oslo_i18n-6.7.0.dist-info/pbr.json
oslo_i18n-6.7.0.dist-info/top_level.txt
oslo_i18n-6.7.0.dist-info/RECORD
